qtwebview2/__init__.py
qtwebview2/exceptions.py
qtwebview2/logger.py
qtwebview2/utils.py
qtwebview2/widget.py
qtwebview2/lib/Microsoft.Web.WebView2.Core.dll
qtwebview2/lib/Microsoft.Web.WebView2.LICENSE.md
qtwebview2/lib/Microsoft.Web.WebView2.WinForms.dll
qtwebview2/lib/runtimes/win-arm64/native/WebView2Loader.dll
qtwebview2/lib/runtimes/win-x64/native/WebView2Loader.dll
qtwebview2/lib/runtimes/win-x86/native/WebView2Loader.dll
qtwebview2-0.1.1.dist-info/licenses/LICENSE
qtwebview2-0.1.1.dist-info/METADATA
qtwebview2-0.1.1.dist-info/WHEEL
qtwebview2-0.1.1.dist-info/top_level.txt
qtwebview2-0.1.1.dist-info/RECORD
