Metadata-Version: 2.4
Name: qtwebview2
Version: 0.1.1
Summary: A lightweight and powerful WebView2 widget for Python Qt (PySide/PyQt) with a seamless JS bridge.
Author-email: 校溯 <xiaosu-1009@qq.com>
License-Expression: MPL-2.0
Project-URL: Homepage, https://github.com/xiaosuyyds/QtWebView2
Keywords: qt,qtpy,pyqt,pyside,web,webview,webview2
Classifier: Development Status :: 4 - Beta
Classifier: Programming Language :: Python :: 3
Classifier: Programming Language :: Python :: 3.8
Classifier: Programming Language :: Python :: 3.9
Classifier: Programming Language :: Python :: 3.10
Classifier: Programming Language :: Python :: 3.11
Classifier: Programming Language :: Python :: 3.12
Classifier: Programming Language :: Python :: 3.13
Classifier: Programming Language :: Python :: 3.14
Classifier: Operating System :: Microsoft :: Windows
Classifier: Intended Audience :: Developers
Classifier: Topic :: Software Development :: Libraries :: Python Modules
Classifier: Topic :: Software Development :: User Interfaces
Requires-Python: >=3.8
License-File: LICENSE
Requires-Dist: pywin32>=300
Requires-Dist: qtpy>=2.0.0
Requires-Dist: pythonnet>=3.0.0
Dynamic: license-file
